aix360i/__init__.py
aix360i/algorithms/__init__.py
aix360i/algorithms/lbbe.cpython-311-x86_64-linux-gnu.so
aix360i/algorithms/input_reduction/INPUT_REDUCTION_bb.cpython-311-x86_64-linux-gnu.so
aix360i/algorithms/input_reduction/INPUT_REDUCTION_bb_text.cpython-311-x86_64-linux-gnu.so
aix360i/algorithms/input_reduction/__init__.py
ibm_metrics_plugin/__init__.py
ibm_metrics_plugin/clients/__init__.py
ibm_metrics_plugin/clients/readers/__init__.py
ibm_metrics_plugin/clients/readers/async_query_executor.cpython-311-x86_64-linux-gnu.so
ibm_metrics_plugin/clients/writers/__init__.py
ibm_metrics_plugin/clients/writers/hive_writer.py
ibm_metrics_plugin/clients/writers/jdbc_writer.py
ibm_metrics_plugin/clients/writers/writer.py
ibm_metrics_plugin/common/__init__.py
ibm_metrics_plugin/common/embedding_generation/__init__.py
ibm_metrics_plugin/common/embedding_generation/default_image_embedding_model.cpython-311-x86_64-linux-gnu.so
ibm_metrics_plugin/common/embedding_generation/default_text_embedding_model.cpython-311-x86_64-linux-gnu.so
ibm_metrics_plugin/common/embedding_generation/embedding_model.cpython-311-x86_64-linux-gnu.so
ibm_metrics_plugin/common/entity/__init__.py
ibm_metrics_plugin/common/entity/config.cpython-311-x86_64-linux-gnu.so
ibm_metrics_plugin/common/utils/__init__.py
ibm_metrics_plugin/common/utils/baseline_data_utils.cpython-311-x86_64-linux-gnu.so
ibm_metrics_plugin/common/utils/client_errors.cpython-311-x86_64-linux-gnu.so
ibm_metrics_plugin/common/utils/configuration_utility.cpython-311-x86_64-linux-gnu.so
ibm_metrics_plugin/common/utils/configuration_utils.cpython-311-x86_64-linux-gnu.so
ibm_metrics_plugin/common/utils/constants.cpython-311-x86_64-linux-gnu.so
ibm_metrics_plugin/common/utils/datetime_util.cpython-311-x86_64-linux-gnu.so
ibm_metrics_plugin/common/utils/ddl_utils_db2.cpython-311-x86_64-linux-gnu.so
ibm_metrics_plugin/common/utils/ddl_utils_hive.cpython-311-x86_64-linux-gnu.so
ibm_metrics_plugin-5.3.0.13.dist-info/METADATA
ibm_metrics_plugin-5.3.0.13.dist-info/WHEEL
ibm_metrics_plugin-5.3.0.13.dist-info/top_level.txt
ibm_metrics_plugin-5.3.0.13.dist-info/RECORD
